sp_adapters/__init__.py
sp_adapters/base.py
sp_adapters/lora.py
sp_adapters/splopa.py
sp_adapters/splora.py
sp_adapters/sppara.py
sp_adapters/torch_pruning.py
sp_adapters/utils.py
structured_pruning_adapters-0.7.1.dist-info/LICENSE
structured_pruning_adapters-0.7.1.dist-info/METADATA
structured_pruning_adapters-0.7.1.dist-info/WHEEL
structured_pruning_adapters-0.7.1.dist-info/top_level.txt
structured_pruning_adapters-0.7.1.dist-info/RECORD
